gevent_socketio_hartwork-0.3.6.post201803091952.dist-info/DESCRIPTION.rst
gevent_socketio_hartwork-0.3.6.post201803091952.dist-info/METADATA
gevent_socketio_hartwork-0.3.6.post201803091952.dist-info/RECORD
gevent_socketio_hartwork-0.3.6.post201803091952.dist-info/WHEEL
gevent_socketio_hartwork-0.3.6.post201803091952.dist-info/entry_points.txt
gevent_socketio_hartwork-0.3.6.post201803091952.dist-info/metadata.json
gevent_socketio_hartwork-0.3.6.post201803091952.dist-info/top_level.txt
socketio/__init__.py
socketio/defaultjson.py
socketio/handler.py
socketio/mixins.py
socketio/namespace.py
socketio/packet.py
socketio/policyserver.py
socketio/sdjango.py
socketio/server.py
socketio/sgunicorn.py
socketio/transports.py
socketio/virtsocket.py
