Metadata-Version: 2.0
Name: gevent-socketio-hartwork
Version: 0.3.6.post201803091952
Summary: SocketIO server based on the Gevent pywsgi server, a Python network library
Home-page: https://github.com/hartwork/gevent-socketio
Author: Sebastian Pipping
Author-email: sebastian@pipping.org
License: BSD
Download-URL: https://github.com/hartwork/gevent-socketio
Platform: UNKNOWN
Classifier: Development Status :: 4 - Beta
Classifier: License :: OSI Approved :: BSD License
Classifier: Programming Language :: Python
Classifier: Operating System :: MacOS :: MacOS X
Classifier: Operating System :: POSIX
Classifier: Topic :: Internet
Classifier: Topic :: Software Development :: Libraries :: Python Modules
Classifier: Intended Audience :: Developers
Requires-Dist: gevent (>=1.1rc5)
Requires-Dist: gevent-websocket
Requires-Dist: six
